Metadata-Version: 2.1
Name: alextbremmidterm
Version: 0.0.1
Summary: Alex Bremner midterm example
Home-page: https://github.com/AlexTBrem/alextbremmidterm
Author: Alex Bremner
Author-email: abremner@vols.utk.edu
License: MIT license
Keywords: alextbremmidterm
Classifier: Development Status :: 2 - Pre-Alpha
Classifier: Intended Audience :: Developers
Classifier: License :: OSI Approved :: MIT License
Classifier: Natural Language :: English
Classifier: Programming Language :: Python :: 3
Classifier: Programming Language :: Python :: 3.7
Classifier: Programming Language :: Python :: 3.8
Classifier: Programming Language :: Python :: 3.9
Classifier: Programming Language :: Python :: 3.10
Requires-Python: >=3.7
License-File: LICENSE
